econfig/__init__.py
econfig/tests.py
econfig-1.0.1.dist-info/DESCRIPTION.rst
econfig-1.0.1.dist-info/METADATA
econfig-1.0.1.dist-info/RECORD
econfig-1.0.1.dist-info/WHEEL
econfig-1.0.1.dist-info/metadata.json
econfig-1.0.1.dist-info/top_level.txt
econfig-1.0.1.dist-info/zip-safe
