Metadata-Version: 2.0
Name: econfig
Version: 1.0.1
Summary: Env variable configuration management
Home-page: https://github.com/onna/envconfig
Author: Nathan Van Gheem
Author-email: nathan@onna.com
License: BSD
Keywords: envronment,config
Platform: UNKNOWN
Classifier: License :: OSI Approved :: BSD License
Classifier: Intended Audience :: Developers
Classifier: Programming Language :: Python :: 3.6
Classifier: Topic :: Software Development :: Libraries :: Python Modules
Provides-Extra: test
Requires-Dist: pytest; extra == 'test'
